Metadata-Version: 2.4
Name: streamlit_notebook
Version: 0.3.1
Summary: A notebook interface for Streamlit.
Author-email: Baptiste Ferrand <bferrand.maths@gmail.com>
License-Expression: MIT
Project-URL: Homepage, https://github.com/B4PT0R/streamlit_notebook
Classifier: Programming Language :: Python :: 3
Classifier: Operating System :: OS Independent
Requires-Python: >=3.9
License-File: LICENSE
Requires-Dist: streamlit-code-editor
Requires-Dist: streamlit>=1.5.0
Requires-Dist: asttokens
Requires-Dist: python-dotenv
Requires-Dist: filetype
Requires-Dist: pydub
Requires-Dist: modict
Provides-Extra: documents
Requires-Dist: requests; extra == "documents"
Requires-Dist: beautifulsoup4; extra == "documents"
Requires-Dist: lxml; extra == "documents"
Requires-Dist: trafilatura; extra == "documents"
Requires-Dist: PyPDF2; extra == "documents"
Requires-Dist: python-docx; extra == "documents"
Requires-Dist: odfpy; extra == "documents"
Requires-Dist: pillow; extra == "documents"
Requires-Dist: selenium; extra == "documents"
Requires-Dist: get-gecko-driver; extra == "documents"
Requires-Dist: pathspec; extra == "documents"
Provides-Extra: agent
Requires-Dist: openai; extra == "agent"
Requires-Dist: numpy; extra == "agent"
Requires-Dist: pydantic; extra == "agent"
Requires-Dist: tiktoken; extra == "agent"
Requires-Dist: regex; extra == "agent"
Requires-Dist: pyyaml; extra == "agent"
Requires-Dist: prompt-toolkit; extra == "agent"
Provides-Extra: agent-full
Requires-Dist: streamlit_notebook[agent]; extra == "agent-full"
Requires-Dist: streamlit_notebook[documents]; extra == "agent-full"
Provides-Extra: datascience
Requires-Dist: matplotlib; extra == "datascience"
Requires-Dist: numpy; extra == "datascience"
Requires-Dist: seaborn; extra == "datascience"
Requires-Dist: pandas; extra == "datascience"
Requires-Dist: pillow; extra == "datascience"
Requires-Dist: openpyxl; extra == "datascience"
Requires-Dist: requests; extra == "datascience"
Requires-Dist: graphviz; extra == "datascience"
Requires-Dist: altair; extra == "datascience"
Requires-Dist: plotly; extra == "datascience"
Requires-Dist: bokeh; extra == "datascience"
Requires-Dist: pydeck; extra == "datascience"
Requires-Dist: scipy; extra == "datascience"
Requires-Dist: sympy; extra == "datascience"
Requires-Dist: scikit-learn; extra == "datascience"
Requires-Dist: vega-datasets; extra == "datascience"
Provides-Extra: full
Requires-Dist: streamlit_notebook[agent-full]; extra == "full"
Requires-Dist: streamlit_notebook[datascience]; extra == "full"
Dynamic: license-file
